pydatamining/__init__.py
pydatamining/controller.py
pydatamining/logger.py
pydatamining/manager/__init__.py
pydatamining/manager/session.py
pydatamining/manager/user_agent.py
pydatamining/proxy/__init__.py
pydatamining/proxy/get.py
pydatamining/proxy/manager.py
pydatamining-1.0.6.dist-info/LICENSE
pydatamining-1.0.6.dist-info/METADATA
pydatamining-1.0.6.dist-info/WHEEL
pydatamining-1.0.6.dist-info/top_level.txt
pydatamining-1.0.6.dist-info/RECORD
