Metadata-Version: 2.1
Name: pydatamining
Version: 1.0.6
Summary: Parser module for send message in Apache Kafka
Home-page: https://github.com/notickets/pydatamining
Author: vladkanatov
Author-email: vlad.kanatik@ya.ru
Classifier: Programming Language :: Python :: 3
Classifier: License :: OSI Approved :: MIT License
Classifier: Operating System :: OS Independent
Requires-Python: >=3.8
License-File: LICENSE
Requires-Dist: aiohappyeyeballs==2.4.4
Requires-Dist: aiohttp==3.11.9
Requires-Dist: aiosignal==1.3.1
Requires-Dist: attrs==24.2.0
Requires-Dist: frozenlist==1.5.0
Requires-Dist: idna==3.10
Requires-Dist: kafka-python==2.0.2
Requires-Dist: loguru==0.7.2
Requires-Dist: multidict==6.1.0
Requires-Dist: propcache==0.2.1
Requires-Dist: python-decouple==3.8
Requires-Dist: yarl==1.18.3
